README.txt
setup.py
liquor/__init__.py
liquor/liquor_analysis.py
liquor/liquor_horse.py
liquor/models.py
liquor/settings.py
liquor.egg-info/PKG-INFO
liquor.egg-info/SOURCES.txt
liquor.egg-info/dependency_links.txt
liquor.egg-info/requires.txt
liquor.egg-info/top_level.txt
liquor/management/__init__.py
liquor/management/commands/__init__.py
liquor/management/commands/analyze_booze.py
liquor/management/commands/steal_booze.py